{
  "data": {
    "sections": [
      {
        "sectionName": "About Your Vehicle",
        "fields": [
          {
            "label": "What’s your car’s registration?",
            "progressBarLabel": "Vehicle Registration",
            "fieldName": "vehicleRegistration",
            "element": "input",
            "type": "text",
            "placeholder": "e.g ABC123",
            "rules": {
              "required": "The vehicles registration number is required",
              "minLength": {
                "value": 3,
                "message": "Registration number must be at least 3 characters long"
              }
            }
          },
          {
            "label": "What kind of vehicle do you drive?",
            "progressBarLabel": "Vehicle type",
            "fieldName": "vehicleType",
            "element": "select",
            "type": "dropdown",
            "placeholder": "Select a vehicle type",
            "options": [
              {
                "label": "Van",
                "value": "van"
              },
              {
                "label": "Car",
                "value": "car"
              },
              {
                "label": "Bike",
                "value": "bike"
              }
            ],
            "rules": {
              "required": "Your vehicle type is required"
            }
          },
          {
            "label": "When did you purchase the vehicle?",
            "progressBarLabel": "Purchase date",
            "fieldName": "vehiclePurchaseDate",
            "element": "input",
            "type": "date",
            "rules": {
              "required": "Purchase date is required"
            },
            "checkbox": "I do not own the vehicle yet"
          },
          {
            "label": "What is the value of the vehicle?",
            "progressBarLabel": "Vehicle value",
            "fieldName": "vehicleValue",
            "icon": "£",
            "element": "input",
            "type": "number",
            "placeholder": "e.g 10000",
            "rules": {
              "required": "The vehicles value is required"
            }
          }
        ]
      },
      {
        "sectionName": "About You",
        "fields": [
          {
            "label": "What is your name?",
            "progressBarLabel": "Name",
            "fieldName": "name",
            "element": "input",
            "type": "text",
            "placeholder": "e.g John Smith",
            "rules": {
              "required": "Name is required",
              "minLength": {
                "value": 2,
                "message": "Name must be at least 2 characters long"
              }
            }
          },
          {
            "label": "What is your date of birth?",
            "progressBarLabel": "Date of birth",
            "fieldName": "dob",
            "element": "input",
            "type": "date",
            "rules": {
              "required": "DOB is required"
            }
          }
        ]
      }
    ]
  }
}
